autodotenv.pth
autodotenv.py
AutoDotEnv-0.1.3.dist-info/LICENSE
AutoDotEnv-0.1.3.dist-info/METADATA
AutoDotEnv-0.1.3.dist-info/WHEEL
AutoDotEnv-0.1.3.dist-info/top_level.txt
AutoDotEnv-0.1.3.dist-info/RECORD
