Metadata-Version: 2.1
Name: AutoDotEnv
Version: 0.1.3
Summary: Automatically set environment variables from .env file when running any Python command.
Home-page: https://github.com/cchurch/autodotenv/
Author: Chris Church
Author-email: chris@ninemoreminutes.com
License: BSD
Project-URL: Documentation, https://github.com/cchurch/autodotenv/
Project-URL: Source, https://github.com/cchurch/autodotenv/
Project-URL: Tracker, https://github.com/cchurch/autodotenv/issues
Keywords: dot env,env file,environ
Platform: UNKNOWN
Classifier: Development Status :: 3 - Alpha
Classifier: Intended Audience :: Developers
Classifier: License :: OSI Approved :: BSD License
Classifier: Operating System :: OS Independent
Classifier: Programming Language :: Python
Classifier: Programming Language :: Python :: 2.7
Classifier: Programming Language :: Python :: 3
Classifier: Programming Language :: Python :: 3.4
Classifier: Programming Language :: Python :: 3.5
Classifier: Programming Language :: Python :: 3.6
Classifier: Programming Language :: Python :: 3.7
Classifier: Programming Language :: Python :: 3.8
Classifier: Programming Language :: Python :: 3.9
Classifier: Topic :: Software Development :: Libraries
Classifier: Topic :: Software Development :: Libraries :: Python Modules
Requires-Dist: python-dotenv
